spikey/__init__.py
spikey/curate/__init__.py
spikey/curate/curate.py
spikey/descriptive/__init__.py
spikey/descriptive/radial.py
spikey/histogram/__init__.py
spikey/histogram/radial.py
spikey/io/__init__.py
spikey/io/spikesort.py
spikey/tuning/__init__.py
spikey/tuning/radial.py
spikey-0.0.5.dist-info/LICENSE
spikey-0.0.5.dist-info/METADATA
spikey-0.0.5.dist-info/WHEEL
spikey-0.0.5.dist-info/top_level.txt
spikey-0.0.5.dist-info/RECORD
